my_package/__init__.py
newtestnew-0.0.1.dist-info/METADATA
newtestnew-0.0.1.dist-info/WHEEL
newtestnew-0.0.1.dist-info/top_level.txt
newtestnew-0.0.1.dist-info/RECORD
