Metadata-Version: 2.4
Name: newtestnew
Version: 0.0.1
Summary: testing for test
Requires-Python: >=3.7
